pynad/__init__.py
pynad/auxiliares.py
pynad/converter.py
pynad/copia_local.py
pynad/metadados.py
pynad/paineis.py
pynad/paineis_id.py
pynad/pynad.py
pynad-3.0.3.dist-info/LICENSE
pynad-3.0.3.dist-info/METADATA
pynad-3.0.3.dist-info/WHEEL
pynad-3.0.3.dist-info/entry_points.txt
pynad-3.0.3.dist-info/top_level.txt
pynad-3.0.3.dist-info/RECORD
