Metadata-Version: 2.1
Name: pynad
Version: 3.0.3
Summary: An application to manage Pnadc microdata and its panels
Author: Rafael Guerreiro Osorio
Author-email: rafael.osorio@ipea.gov.br
Classifier: Programming Language :: Python :: 3
Classifier: License :: OSI Approved :: GNU General Public License v3 or later (GPLv3+)
Classifier: Operating System :: OS Independent
Requires-Python: >=3.6
License-File: LICENSE
Requires-Dist: pyarrow
Requires-Dist: xlrd
